Metadata-Version: 2.1
Name: autoalbument
Version: 0.4.0
Summary: AutoML for image augmentation
Home-page: https://github.com/albumentations-team/autoalbument
Author: Alex Parinov, Vladimir Iglovikov, Eugene Khvedchenya, Druzhinin Mikhail, Buslaev Alexander
License: MIT
Platform: UNKNOWN
Classifier: Development Status :: 4 - Beta
Classifier: License :: OSI Approved :: MIT License
Classifier: Intended Audience :: Developers
Classifier: Intended Audience :: Science/Research
Classifier: Operating System :: OS Independent
Classifier: Programming Language :: Python
Classifier: Programming Language :: Python :: 3
Classifier: Programming Language :: Python :: 3.6
Classifier: Programming Language :: Python :: 3.7
Classifier: Programming Language :: Python :: 3.8
Classifier: Topic :: Software Development :: Libraries
Classifier: Topic :: Software Development :: Libraries :: Python Modules
Requires-Dist: albumentations (>=0.5.1)
Requires-Dist: pytorch-lightning (<1.2,>=1.1.8)
Requires-Dist: torch (>=1.6.0)
Requires-Dist: hydra-core (>=1.0)
Requires-Dist: timm (==0.3.2)
Requires-Dist: segmentation-models-pytorch (>=0.1.3)
Requires-Dist: tqdm
Requires-Dist: click
Requires-Dist: colorama
Requires-Dist: tensorboard
Requires-Dist: ruamel.yaml
Provides-Extra: tests
Requires-Dist: pytest ; extra == 'tests'
